wajiwaji/__init__.py
wajiwaji/hello.py
wajiwaji-0.0.1.data/scripts/wajiwaji
wajiwaji-0.0.1.dist-info/DESCRIPTION.rst
wajiwaji-0.0.1.dist-info/METADATA
wajiwaji-0.0.1.dist-info/RECORD
wajiwaji-0.0.1.dist-info/WHEEL
wajiwaji-0.0.1.dist-info/metadata.json
wajiwaji-0.0.1.dist-info/top_level.txt
