Metadata-Version: 2.0
Name: wajiwaji
Version: 0.0.1
Summary: Hello I'm wajiwaji :-)
Home-page: https://github.com/hisato-kawaji/pypi-test
Author: Hisato Kawaji
Author-email: hisato.kawaji@gmail.com
License: MIT License
Platform: UNKNOWN
Classifier: Programming Language :: Python :: 3.6
Classifier: License :: OSI Approved :: MIT License
